README.rst
setup.py
conductr_cli/__init__.py
conductr_cli/ansi_colors.py
conductr_cli/bndl.py
conductr_cli/bndl_create.py
conductr_cli/bndl_docker.py
conductr_cli/bndl_main.py
conductr_cli/bndl_oci.py
conductr_cli/bndl_utils.py
conductr_cli/bundle_core_info.py
conductr_cli/bundle_deploy.py
conductr_cli/bundle_deploy_v2.py
conductr_cli/bundle_deploy_v3.py
conductr_cli/bundle_installation.py
conductr_cli/bundle_scale.py
conductr_cli/bundle_shorthand.py
conductr_cli/bundle_utils.py
conductr_cli/bundle_validation.py
conductr_cli/bytes_util.py
conductr_cli/conduct.py
conductr_cli/conduct_acls.py
conductr_cli/conduct_agents.py
conductr_cli/conduct_dcos.py
conductr_cli/conduct_deploy.py
conductr_cli/conduct_deploy_bintray.py
conductr_cli/conduct_deploy_bundle.py
conductr_cli/conduct_events.py
conductr_cli/conduct_info.py
conductr_cli/conduct_info_common.py
conductr_cli/conduct_info_inspect.py
conductr_cli/conduct_info_list.py
conductr_cli/conduct_load.py
conductr_cli/conduct_load_license.py
conductr_cli/conduct_logs.py
conductr_cli/conduct_main.py
conductr_cli/conduct_members.py
conductr_cli/conduct_request.py
conductr_cli/conduct_run.py
conductr_cli/conduct_service_names.py
conductr_cli/conduct_stop.py
conductr_cli/conduct_unload.py
conductr_cli/conduct_url.py
conductr_cli/conductr_backup.py
conductr_cli/conductr_restore.py
conductr_cli/constants.py
conductr_cli/control_protocol.py
conductr_cli/custom_settings.py
conductr_cli/data_structure_utils.py
conductr_cli/docker.py
conductr_cli/endpoint.py
conductr_cli/exceptions.py
conductr_cli/host.py
conductr_cli/http.py
conductr_cli/license.py
conductr_cli/license_auth.py
conductr_cli/license_validation.py
conductr_cli/logging_setup.py
conductr_cli/main_handler.py
conductr_cli/pyinstaller_info.py
conductr_cli/resolver.py
conductr_cli/sandbox.py
conductr_cli/sandbox_common.py
conductr_cli/sandbox_features.py
conductr_cli/sandbox_logs.py
conductr_cli/sandbox_main.py
conductr_cli/sandbox_proxy.py
conductr_cli/sandbox_ps.py
conductr_cli.egg-info/PKG-INFO
conductr_cli.egg-info/SOURCES.txt
conductr_cli.egg-info/dependency_links.txt
conductr_cli.egg-info/entry_points.txt
conductr_cli.egg-info/requires.txt
conductr_cli.egg-info/top_level.txt
