Metadata-Version: 1.0
Name: conductr-cli
Version: 1.2.25
Summary: A CLI client for Lightbend ConductR
Home-page: https://github.com/typesafehub/conductr-cli
Author: UNKNOWN
Author-email: UNKNOWN
License: Apache 2
Platform: UNKNOWN
